<?xml version="1.0" encoding="UTF-8" standalone="yes"?>
<!-- instance Draupnir_Cave 
aionchs-Wylovech-->
<spawns>
    <!--Bakarma scaleguard -->
    <spawn map="320080000" npcid="213376" pool="2" interval="1200">
       <object x="395.90402" y="606.67664" z="597.9613" h="88"/>
       <object x="398.85376" y="577.7569" z="599.8154" h="29"/>
    </spawn>
    <!-- Bakarma scaleguard-->
    <spawn map="320080000" npcid="213377" pool="4" interval="1200">
       <object x="491.20874" y="401.75433" z="614.5058" h="102"/>
       <object x="471.84668" y="405.82108" z="614.57306" h="6"/>
       <object x="499.91214" y="421.3018" z="617.47375" h="77"/>
       <object x="374.4023" y="713.8165" z="590.4289" h="113"/>
    </spawn>
    <!-- Bakarma scalewatch-->
    <spawn map="320080000" npcid="213378" pool="2" interval="1200">
       <object x="555.9266" y="621.6363" z="578.26483" h="71"/>
       <object x="558.21844" y="618.9637" z="578.4327" h="93"/>
    </spawn>
    <!--Bakarma scaleblade -->
    <spawn map="320080000" npcid="213379" pool="3" interval="1200">
       <object x="454.0893" y="506.75742" z="615.34393" h="108"/>
       <object x="458.54614" y="514.12024" z="615.84357" h="103"/>
       <object x="264.3094" y="693.4969" z="599.8212" h="118"/>
    </spawn>
    <!--Bakarma scaleblade -->
    <spawn map="320080000" npcid="213380" pool="14" interval="1200">
       <object x="489.8585" y="391.92657" z="614.3682" h="94"/>
       <object x="500.97202" y="393.4702" z="617.0133" h="81"/>
       <object x="478.4944" y="441.2953" z="615.0648" h="97"/>
       <object x="472.5726" y="426.7122" z="613.5492" h="115"/>
       <object x="470.23102" y="416.42526" z="613.897" h="114"/>
       <object x="389.8145" y="566.8687" z="601.7806" h="8"/>
       <object x="366.16583" y="587.62616" z="601.7785" h="7"/>
       <object x="378.8346" y="640.0117" z="599.2635" h="109"/>
       <object x="393.34186" y="709.2977" z="586.83606" h="99"/>
       <object x="387.85773" y="704.12317" z="586.5031" h="103"/>
       <object x="357.21335" y="704.95514" z="597.5286" h="1"/>
       <object x="356.23502" y="714.0379" z="597.0484" h="0"/>
       <object x="332.93906" y="699.105" z="597.7959" h="3"/>
       <object x="331.16907" y="711.3204" z="597.6317" h="113"/>
    </spawn>
    <!--Bakarma dragonblade -->
    <spawn map="320080000" npcid="213381" pool="1" interval="1200">
       <object x="580.0676" y="606.4752" z="578.6417" h="70"/>
    </spawn>
    <!--Bakarma fangguard -->
    <spawn map="320080000" npcid="213382" pool="3" interval="1200">
       <object x="456.61005" y="442.43457" z="620.26575" h="89"/>
       <object x="393.2788" y="563.7119" z="601.70624" h="23"/>
       <object x="582.33234" y="613.5438" z="579.96375" h="26"/>
    </spawn>
    <!-- Bakarma comitatus-->
    <spawn map="320080000" npcid="213385" pool="1" interval="1200">
       <object x="456.1817" y="411.15277" z="619.32556" h="50"/>
    </spawn>
    <!-- Bakarma comitatus-->
    <spawn map="320080000" npcid="213386" pool="2" interval="1200">
       <object x="382.43124" y="614.89105" z="597.93054" h="105"/>
       <object x="377.70728" y="613.2934" z="598.76416" h="93"/>
    </spawn>
    <!-- Bakarma destroyer-->
    <spawn map="320080000" npcid="213387" pool="1" interval="1200">
       <object x="537.9755" y="438.161" z="614.574" h="101"/>
    </spawn>
    <!--Bakarma shadowscale -->
    <spawn map="320080000" npcid="213388" pool="3" interval="1200">
       <object x="511.24246" y="464.80466" z="614.3309" h="42"/>
       <object x="517.3385" y="473.41315" z="615.2313" h="62"/>
       <object x="548.05804" y="433.18307" z="613.591" h="65"/>
    </spawn>
    <!-- Bakarma shadowscale-->
    <spawn map="320080000" npcid="213389" pool="13" interval="1200">
       <object x="403.35312" y="590.74066" z="600.706" h="92"/>
       <object x="406.54752" y="612.3756" z="599.3836" h="79"/>
       <object x="396.2637" y="625.05206" z="597.5963" h="75"/>
       <object x="362.45184" y="609.73834" z="601.62036" h="113"/>
       <object x="374.32294" y="621.99396" z="598.50055" h="95"/>
       <object x="327.9256" y="688.03845" z="597.2513" h="43"/>
       <object x="325.37296" y="684.6775" z="596.90985" h="32"/>
       <object x="321.7422" y="724.1284" z="597.0442" h="100"/>
       <object x="317.7177" y="597.9834" z="500.78247" h="96"/>
       <object x="311.0072" y="602.3358" z="499.90262" h="40"/>
       <object x="316.55957" y="618.21106" z="497.29425" h="14"/>
       <object x="329.37823" y="655.29254" z="492.81717" h="88"/>
       <object x="351.55695" y="667.00275" z="490.04486" h="1"/>
    </spawn>
    <!--Bakarma fangblade -->
    <spawn map="320080000" npcid="213391" pool="1" interval="1200">
       <object x="471.3296" y="597.50195" z="512.84174" h="62"/>
    </spawn>
    <!--Bakarma fangblade -->
    <spawn map="320080000" npcid="213392" pool="6" interval="1200">
       <object x="419.0449" y="577.04706" z="600.2793" h="71"/>
       <object x="307.1444" y="677.43396" z="596.64435" h="25"/>
       <object x="286.24826" y="718.34796" z="596.8975" h="105"/>
       <object x="303.9292" y="729.28357" z="596.958" h="84"/>
       <object x="302.4881" y="729.905" z="596.8229" h="82"/>
       <object x="577.6449" y="639.1754" z="582.5656" h="77"/>
    </spawn>
    <!-- Trained monitor-->
    <spawn map="320080000" npcid="213397" pool="3" interval="1200">
       <object x="395.32172" y="509.3701" z="514.0723" h="3"/>
       <object x="369.71234" y="515.94586" z="511.4521" h="55"/>
       <object x="353.03836" y="534.8215" z="511.69455" h="99"/>
    </spawn>
    <!-- Bakarma ranger-->
    <spawn map="320080000" npcid="213400" pool="3" interval="1200">
       <object x="452.30777" y="453.47357" z="624.76636" h="69"/>
       <object x="476.2314" y="454.36932" z="627.6022" h="52"/>
       <object x="339.55847" y="706.1146" z="598.2368" h="3"/>
    </spawn>
    <!-- Bakarma ranger-->
    <spawn map="320080000" npcid="213401" pool="4" interval="1200">
       <object x="461.7136" y="506.1424" z="616.6666" h="105"/>
       <object x="392.268" y="667.72986" z="599.1859" h="96"/>
       <object x="561.808" y="635.32135" z="579.44086" h="48"/>
       <object x="554.0452" y="640.3522" z="578.67755" h="110"/>
    </spawn>
    <!-- Bakarma mystic-->
    <spawn map="320080000" npcid="213409" pool="8" interval="1200">
       <object x="453.12292" y="413.52304" z="619.2767" h="19"/>
       <object x="444.16592" y="425.67505" z="619.2469" h="119"/>
       <object x="462.6165" y="464.3653" z="623.43225" h="91"/>
       <object x="391.4407" y="636.9211" z="599.5608" h="51"/>
       <object x="305.63672" y="677.26324" z="596.70636" h="32"/>
       <object x="265.52176" y="701.38586" z="599.9987" h="114"/>
       <object x="284.58453" y="716.2725" z="596.8169" h="105"/>
       <object x="324.75864" y="724.7625" z="597.5997" h="92"/>
    </spawn>
    <!-- Bakarma mystic-->
    <spawn map="320080000" npcid="213410" pool="4" interval="1200">
       <object x="513.785" y="448.24915" z="615.3595" h="36"/>
       <object x="523.6416" y="431.74103" z="615.1249" h="74"/>
       <object x="540.6458" y="441.7848" z="615.07117" h="46"/>
       <object x="531.7024" y="456.8226" z="615.1051" h="49"/>
    </spawn>
    <!-- Bakarma mender-->
    <spawn map="320080000" npcid="213411" pool="1" interval="1200">
       <object x="324.09164" y="687.501" z="596.8752" h="24"/>
    </spawn>
    <!--Bakarma outlaw -->
    <spawn map="320080000" npcid="213412" pool="1" interval="1200">
       <object x="407.84344" y="669.7567" z="593.63745" h="47"/>
    </spawn>
    <!--Bakarma headhunter -->
    <spawn map="320080000" npcid="213414" pool="1" interval="1200">
       <object x="408.64423" y="671.5848" z="592.8562" h="38"/>
    </spawn>
    <!--Bakarma protector -->
    <spawn map="320080000" npcid="213416" pool="1" interval="1200">
       <object x="391.69394" y="648.16327" z="597.0437" h="85"/>
    </spawn>
    <!-- Bakarma protector-->
    <spawn map="320080000" npcid="213417" pool="3" interval="1200">
       <object x="412.448" y="687.8717" z="588.2567" h="69"/>
       <object x="338.69818" y="540.03827" z="510.81424" h="114"/>
       <object x="301.66263" y="576.1616" z="506.79172" h="107"/>
    </spawn>
    <!-- Bakarma scourge-->
    <spawn map="320080000" npcid="213420" pool="3" interval="1200">
       <object x="387.09607" y="679.21545" z="481.50778" h="60"/>
       <object x="387.14557" y="670.5194" z="482.0092" h="62"/>
       <object x="425.28064" y="648.71686" z="472.90146" h="19"/>
    </spawn>
    <!-- Bakarma mutilator-->
    <spawn map="320080000" npcid="213423" pool="4" interval="1200">
       <object x="652.42554" y="415.75488" z="322.43503" h="114"/>
       <object x="637.1179" y="412.03635" z="319.49487" h="47"/>
       <object x="645.9048" y="452.307" z="309.66125" h="14"/>
       <object x="650.87994" y="448.56824" z="310.07196" h="18"/>
    </spawn>
    <!-- Bakarma lifeender-->
    <spawn map="320080000" npcid="213424" pool="2" interval="1200">
       <object x="581.21356" y="445.38855" z="445.8218" h="20"/>
       <object x="597.11597" y="461.76758" z="442.62012" h="118"/>
    </spawn>
    <!--Bakarma deathbringer -->
    <spawn map="320080000" npcid="213426" pool="3" interval="1200">
       <object x="625.39923" y="444.86856" z="311.31445" h="110"/>
       <object x="623.42285" y="423.72943" z="312.03113" h="15"/>
       <object x="653.27826" y="434.12927" z="310.0457" h="54"/>
    </spawn>
    <!--Bakarma guardian -->
    <spawn map="320080000" npcid="213427" pool="3" interval="1200">
       <object x="534.16547" y="592.26935" z="580.0588" h="115"/>
       <object x="636.8527" y="425.84613" z="446.1028" h="48"/>
       <object x="639.87225" y="429.62115" z="446.21576" h="46"/>
    </spawn>
    <!--Bakarma dragonpriest -->
    <spawn map="320080000" npcid="213432" pool="3" interval="1200">
       <object x="635.84955" y="409.2793" z="319.48624" h="33"/>
       <object x="618.77783" y="436.29297" z="312.21066" h="119"/>
       <object x="651.6681" y="428.197" z="310.13284" h="57"/>
    </spawn>
    <!--Vicious energy -->
    <spawn map="320080000" npcid="213436" pool="1" interval="1200">
       <object x="218.76894" y="673.91125" z="523.3829" h="80"/>
    </spawn>
    <!--Bakarma lifegrabber -->
    <spawn map="320080000" npcid="213437" pool="2" interval="1200">
       <object x="532.1641" y="613.4089" z="578.92163" h="117"/>
       <object x="544.4084" y="632.1149" z="577.5246" h="24"/>
    </spawn>
    <!--Bakarma lifegrabber -->
    <spawn map="320080000" npcid="213438" pool="1" interval="1200">
       <object x="646.39044" y="421.28104" z="445.87845" h="46"/>
    </spawn>
    <!-- Bakarma cursewitch-->
    <spawn map="320080000" npcid="213445" pool="1" interval="1200">
       <object x="576.84607" y="452.56714" z="444.9203" h="27"/>
    </spawn>
    <!-- Bakarma bloodlock-->
    <spawn map="320080000" npcid="213446" pool="2" interval="1200">
       <object x="658.0789" y="415.97583" z="444.6894" h="31"/>
       <object x="637.5218" y="431.56607" z="311.61685" h="62"/>
    </spawn>
    <!-- Bakarma bloodlock-->
    <spawn map="320080000" npcid="213447" pool="1" interval="1200">
       <object x="649.7584" y="408.80933" z="322.91556" h="10"/>
    </spawn>
    <!-- Worldbender's minion-->
    <spawn map="320080000" npcid="213449" pool="1" interval="1200">
       <object x="451.30756" y="674.2777" z="466.2672" h="64"/>
    </spawn>
    <!--Worldbender's minion -->
    <spawn map="320080000" npcid="213451" pool="1" interval="1200">
       <object x="651.67377" y="406.2962" z="323.16013" h="10"/>
    </spawn>
    <!-- Worldbender's minion-->
    <spawn map="320080000" npcid="213452" pool="1" interval="1200">
       <object x="659.74023" y="415.15143" z="444.90005" h="29"/>
    </spawn>
    <!-- Worldbender's minion-->
    <spawn map="320080000" npcid="213454" pool="4" interval="1200">
       <object x="590.37775" y="447.78152" z="446.30923" h="12"/>
       <object x="613.8873" y="451.66437" z="445.2002" h="69"/>
       <object x="610.92944" y="471.57224" z="443.1403" h="66"/>
       <object x="594.93964" y="473.91016" z="442.70465" h="66"/>
    </spawn>
    <!--Worldbender's minion -->
    <spawn map="320080000" npcid="213455" pool="3" interval="1200">
       <object x="205.41747" y="652.572" z="523.77435" h="5"/>
       <object x="186.342" y="664.7776" z="524.26685" h="3"/>
       <object x="636.3527" y="430.6262" z="311.66745" h="42"/>
    </spawn>
    <!-- Bakarma scaleguard-->
    <spawn map="320080000" npcid="213457" pool="2" interval="1200">
       <object x="480.80817" y="483.572" z="620.9148" h="86"/>
       <object x="427.31558" y="535.646" z="606.484" h="103"/>
    </spawn>
    <!-- Bakarma scaleguard-->
    <spawn map="320080000" npcid="213459" pool="1" interval="1200">
       <object x="535.4125" y="597.09644" z="579.0821" h="3"/>
    </spawn>
    <!-- Bakarma scaleguard-->
    <spawn map="320080000" npcid="213460" pool="1" interval="1200">
       <object x="476.0127" y="655.75977" z="581.8394" h="26"/>
    </spawn>
    <!-- Bakarma dragonblade-->
    <spawn map="320080000" npcid="213461" pool="1" interval="1200">
       <object x="483.37106" y="653.78455" z="580.739" h="19"/>
       <object x="484.35068" y="583.5889" z="513.329" h="0"/>
    </spawn>
    <!-- Bakarma fangguard-->
    <spawn map="320080000" npcid="213463" pool="1" interval="1200">
       <object x="428.18915" y="552.23425" z="606.34204" h="79"/>
    </spawn>
    <!--Bakarma clawguard -->
    <spawn map="320080000" npcid="213464" pool="3" interval="1200">
       <object x="566.92065" y="554.7171" z="574.71" h="47"/>
       <object x="572.40356" y="560.5067" z="574.2939" h="52"/>
       <object x="412.80826" y="667.6466" z="473.9614" h="53"/>
    </spawn>
    <!-- Bakarma shadowscale-->
    <spawn map="320080000" npcid="213465" pool="4" interval="1200">
       <object x="504.53027" y="686.1687" z="587.0396" h="83"/>
       <object x="528.01404" y="664.58545" z="581.0101" h="0"/>
       <object x="448.9188" y="610.64386" z="509.4865" h="45"/>
       <object x="451.09012" y="605.5067" z="509.55075" h="104"/>
    </spawn>
    <!-- Bakarma shadowscale-->
    <spawn map="320080000" npcid="213466" pool="7" interval="1200">
       <object x="425.4587" y="523.4179" z="609.1438" h="114"/>
       <object x="482.05084" y="555.21735" z="511.84302" h="58"/>
       <object x="510.4976" y="575.1184" z="509.60858" h="114"/>
       <object x="177.687" y="542.6339" z="504.20483" h="7"/>
       <object x="193.63881" y="551.82166" z="503.27823" h="69"/>
       <object x="184.02768" y="546.88446" z="503.42273" h="46"/>
       <object x="162.8943" y="541.3322" z="504.10605" h="63"/>
    </spawn>
    <!-- Bakarma mistscale-->
    <spawn map="320080000" npcid="213467" pool="4" interval="1200">
       <object x="305.50183" y="699.0553" z="598.27185" h="93"/>
       <object x="301.93085" y="695.11334" z="598.28265" h="73"/>
       <object x="294.9369" y="696.2619" z="598.3049" h="38"/>
       <object x="295.00684" y="700.33734" z="598.42596" h="0"/>
    </spawn>
    <!-- Bakarma breeder-->
    <spawn map="320080000" npcid="213469" pool="3" interval="1200">
       <object x="397.25885" y="509.78027" z="514.8871" h="114"/>
       <object x="370.3278" y="514.5079" z="511.6896" h="90"/>
       <object x="354.8599" y="532.9965" z="511.79004" h="88"/>
    </spawn>
    <!-- Bakarma ranger-->
    <spawn map="320080000" npcid="213471" pool="3" interval="1200">
       <object x="478.6192" y="691.02655" z="584.3722" h="43"/>
       <object x="559.3867" y="596.78687" z="575.62085" h="18"/>
       <object x="566.16064" y="586.23517" z="574.3941" h="65"/>
    </spawn>
    <!--Bakarma searcher -->
    <spawn map="320080000" npcid="213472" pool="1" interval="1200">
       <object x="480.74417" y="691.6491" z="584.47906" h="43"/>
    </spawn>
    <!-- Bakarma shadowshot-->
    <spawn map="320080000" npcid="213474" pool="4" interval="1200">
       <object x="614.1604" y="554.4178" z="564.6333" h="12"/>
       <object x="637.75653" y="572.6751" z="557.9656" h="19"/>
       <object x="657.73267" y="586.9303" z="555.74304" h="13"/>
       <object x="597.628" y="670.531" z="543.9469" h="87"/>
    </spawn>
    <!--Bakarma mystic -->
    <spawn map="320080000" npcid="213477" pool="1" interval="1200">
       <object x="469.28897" y="699.6399" z="587.91095" h="98"/>
    </spawn>
    <!--Bakarma outlaw -->
    <spawn map="320080000" npcid="213479" pool="2" interval="1200">
       <object x="578.91394" y="664.89215" z="540.64246" h="6"/>
       <object x="581.87366" y="659.5026" z="541.0904" h="12"/>
    </spawn>
    <!--Bakarma headhunter -->
    <spawn map="320080000" npcid="213482" pool="4" interval="1200">
       <object x="233.87901" y="601.25464" z="512.9604" h="105"/>
       <object x="236.4786" y="607.84174" z="513.14343" h="107"/>
       <object x="192.57918" y="618.9079" z="504.2482" h="10"/>
       <object x="195.31888" y="612.0891" z="505.0484" h="9"/>
    </spawn>
    <!--Bakarma scourge -->
    <spawn map="320080000" npcid="213484" pool="2" interval="1200">
       <object x="313.98734" y="567.9818" z="505.1249" h="106"/>
       <object x="311.65695" y="563.8529" z="505.8797" h="110"/>
    </spawn>
    <!-- Bakarma mutilator-->
    <spawn map="320080000" npcid="213487" pool="5" interval="1200">
       <object x="435.87628" y="565.0584" z="511.67258" h="15"/>
       <object x="440.7379" y="561.0709" z="511.53427" h="17"/>
       <object x="424.98367" y="514.321" z="518.4869" h="17"/>
       <object x="420.4052" y="521.372" z="518.1067" h="20"/>
       <object x="326.99506" y="574.1438" z="503.71133" h="67"/>
    </spawn>
    <!-- Bakarma deathbringer-->
    <spawn map="320080000" npcid="213489" pool="1" interval="1200">
       <object x="471.69116" y="586.75275" z="512.5508" h="43"/>
    </spawn>
    <!-- Bakarma deathbringer-->
    <spawn map="320080000" npcid="213490" pool="10" interval="1200">
       <object x="488.19278" y="602.4596" z="512.7917" h="94"/>
       <object x="210.69997" y="691.4487" z="525.62854" h="94"/>
       <object x="198.72076" y="684.7644" z="525.51483" h="96"/>
       <object x="189.56725" y="671.78076" z="524.7397" h="1"/>
       <object x="179.51497" y="687.4935" z="526.9458" h="33"/>
       <object x="221.3659" y="712.7407" z="526.62555" h="110"/>
       <object x="240.51936" y="702.76306" z="527.7474" h="18"/>
       <object x="241.00056" y="709.75714" z="527.90936" h="36"/>
       <object x="461.2086" y="665.1094" z="457.54608" h="56"/>
       <object x="461.30032" y="663.4925" z="457.37045" h="60"/>
    </spawn>
    <!-- Bakarma guardian-->
    <spawn map="320080000" npcid="213491" pool="21" interval="1200">
       <object x="539.15576" y="657.39246" z="528.6863" h="14"/>
       <object x="534.7728" y="662.57477" z="528.88885" h="21"/>
       <object x="511.60397" y="601.6317" z="512.89825" h="29"/>
       <object x="289.8121" y="568.597" z="511.2385" h="18"/>
       <object x="281.8724" y="571.61957" z="511.86398" h="23"/>
       <object x="184.7679" y="586.99335" z="502.3376" h="36"/>
       <object x="187.55208" y="592.28015" z="502.35635" h="49"/>
       <object x="174.67885" y="568.3265" z="501.99304" h="40"/>
       <object x="178.96245" y="570.0445" z="502.45956" h="37"/>
       <object x="253.86201" y="621.3933" z="517.1584" h="93"/>
       <object x="261.69672" y="625.24036" z="517.7514" h="97"/>
       <object x="224.36005" y="643.40326" z="524.76324" h="111"/>
       <object x="230.72745" y="649.9733" z="524.04205" h="105"/>
       <object x="183.02814" y="718.9714" z="529.7642" h="85"/>
       <object x="189.25594" y="720.84546" z="529.7642" h="93"/>
       <object x="247.29466" y="466.6762" z="505.9019" h="30"/>
       <object x="237.93907" y="466.79007" z="505.72992" h="28"/>
       <object x="534.67285" y="497.6937" z="448.60974" h="29"/>
       <object x="528.3114" y="492.88184" z="449.26355" h="40"/>
       <object x="570.4212" y="474.55057" z="445.23196" h="60"/>
       <object x="570.92523" y="466.58292" z="445.49164" h="60"/>
    </spawn>
    <!--Bakarma mendicant -->
    <spawn map="320080000" npcid="213494" pool="4" interval="1200">
       <object x="186.02188" y="652.04236" z="525.3997" h="18"/>
       <object x="175.8651" y="676.5022" z="525.7414" h="4"/>
       <object x="256.49197" y="443.45563" z="512.8898" h="99"/>
       <object x="210.42221" y="463.06955" z="511.53485" h="63"/>
    </spawn>
    <!-- Bakarma dragonpriest-->
    <spawn map="320080000" npcid="213495" pool="2" interval="1200">
       <object x="242.42372" y="705.8044" z="528.0825" h="61"/>
       <object x="175.12541" y="662.2319" z="525.2751" h="11"/>
    </spawn>
    <!--Bakarma deathpriest -->
    <spawn map="320080000" npcid="213497" pool="1" interval="1200">
       <object x="474.5527" y="663.7943" z="461.83737" h="45"/>
    </spawn>
    <!--Bakarma lifegrabber -->
    <spawn map="320080000" npcid="213498" pool="11" interval="1200">
       <object x="585.57355" y="551.4317" z="571.18933" h="50"/>
       <object x="568.5974" y="663.4713" z="536.9337" h="57"/>
       <object x="526.84454" y="649.1414" z="524.71423" h="84"/>
       <object x="530.6593" y="622.12085" z="518.16595" h="87"/>
       <object x="271.23248" y="592.923" z="513.9957" h="106"/>
       <object x="217.82701" y="618.53" z="507.97626" h="52"/>
       <object x="138.75198" y="558.082" z="502.0683" h="16"/>
       <object x="248.16724" y="634.91626" z="521.36835" h="105"/>
       <object x="246.88086" y="498.31506" z="500.36212" h="27"/>
       <object x="258.18945" y="527.2869" z="503.8863" h="17"/>
       <object x="318.29465" y="582.3504" z="502.27805" h="33"/>
    </spawn>
    <!-- Bakarma lifegrabber-->
    <spawn map="320080000" npcid="213499" pool="15" interval="1200">
       <object x="492.3974" y="615.31323" z="512.3092" h="100"/>
       <object x="498.7471" y="588.85004" z="511.66617" h="25"/>
       <object x="491.53256" y="572.7223" z="510.97388" h="71"/>
       <object x="435.7741" y="547.624" z="512.34576" h="97"/>
       <object x="434.04633" y="530.8035" z="515.0508" h="12"/>
       <object x="158.75145" y="607.3084" z="500.0117" h="96"/>
       <object x="156.41139" y="579.4716" z="500.4153" h="99"/>
       <object x="141.73056" y="603.17474" z="499.43307" h="101"/>
       <object x="179.30283" y="576.9552" z="502.56552" h="35"/>
       <object x="182.96863" y="608.333" z="501.87665" h="10"/>
       <object x="209.73079" y="703.65924" z="526.64386" h="77"/>
       <object x="196.10588" y="693.4609" z="526.5474" h="74"/>
       <object x="214.26756" y="658.7267" z="523.65546" h="106"/>
       <object x="535.882" y="485.99695" z="449.97415" h="39"/>
       <object x="579.477" y="469.8147" z="443.45755" h="115"/>
    </spawn>
    <!-- Bakarma soultwister-->
    <spawn map="320080000" npcid="213500" pool="4" interval="1200">
       <object x="480.26407" y="624.72125" z="512.12427" h="93"/>
       <object x="198.98303" y="714.91003" z="529.3255" h="116"/>
       <object x="184.04309" y="707.9347" z="529.37506" h="93"/>
       <object x="228.88754" y="685.5884" z="524.9005" h="58"/>
    </spawn>
    <!-- Bakarma black mage-->
    <spawn map="320080000" npcid="213501" pool="3" interval="1200">
       <object x="190.68858" y="587.5118" z="502.99753" h="57"/>
       <object x="169.97937" y="626.41626" z="502.1991" h="101"/>
       <object x="219.26823" y="672.2207" z="523.6324" h="81"/>
    </spawn>
    <!--Bakarma cursewitch -->
    <spawn map="320080000" npcid="213503" pool="10" interval="1200">
       <object x="172.13626" y="601.9809" z="500.84006" h="66"/>
       <object x="174.40007" y="622.16565" z="502.3189" h="42"/>
       <object x="157.49405" y="629.6383" z="501.62012" h="51"/>
       <object x="138.12833" y="623.9002" z="500.68976" h="63"/>
       <object x="134.22401" y="612.73816" z="500.2372" h="87"/>
       <object x="139.98328" y="597.893" z="499.6863" h="103"/>
       <object x="136.85226" y="574.6796" z="499.98682" h="71"/>
       <object x="122.99629" y="569.4916" z="494.78772" h="36"/>
       <object x="115.52925" y="567.0887" z="494.80054" h="99"/>
       <object x="587.6945" y="480.2758" z="443.8812" h="83"/>
    </spawn>
    <!-- Bakarma bloodlock-->
    <spawn map="320080000" npcid="213505" pool="3" interval="1200">
       <object x="204.98286" y="654.90247" z="523.7712" h="20"/>
       <object x="186.84547" y="663.6285" z="524.1782" h="7"/>
       <object x="450.41388" y="675.8496" z="466.52417" h="67"/>
    </spawn>
    <!--Bakarma bloodlock -->
    <spawn map="320080000" npcid="213506" pool="8" interval="1200">
       <object x="151.03308" y="568.5656" z="502.24963" h="18"/>
       <object x="166.69371" y="582.1573" z="502.45117" h="13"/>
       <object x="158.19609" y="619.6489" z="501.97882" h="40"/>
       <object x="148.59239" y="604.8643" z="500.59033" h="81"/>
       <object x="593.73553" y="475.36185" z="443.0138" h="72"/>
       <object x="609.76074" y="472.793" z="443.129" h="78"/>
       <object x="613.08966" y="452.88034" z="445.27356" h="76"/>
       <object x="591.7062" y="446.53296" z="446.18677" h="14"/>
    </spawn>
    <!-- Bakarma drakeblade-->
    <spawn map="320080000" npcid="213551" pool="2" interval="1200">
       <object x="446.19846" y="703.9693" z="584.129" h="82"/>
       <object x="442.0489" y="702.533" z="582.82965" h="51"/>
    </spawn>
    <!--Bakarma lifecrusher -->
    <spawn map="320080000" npcid="213552" pool="1" interval="1200">
       <object x="477.8276" y="604.8587" z="512.72205" h="18"/>
    </spawn>
    <!--Bakarma flameraider -->
    <spawn map="320080000" npcid="213553" pool="1" interval="1200">
       <object x="481.6965" y="600.4075" z="513.7992" h="77"/>
    </spawn>
    <!-- Bakarma grappler-->
    <spawn map="320080000" npcid="213554" pool="4" interval="1200">
       <object x="299.57" y="702.7766" z="598.3645" h="83"/>
       <object x="303.13043" y="702.0623" z="598.28375" h="76"/>
       <object x="297.41068" y="692.7529" z="598.25183" h="52"/>
       <object x="300.38977" y="693.5014" z="598.279" h="35"/>
    </spawn>
    <!--Bakarma mender -->
    <spawn map="320080000" npcid="213556" pool="3" interval="1200">
       <object x="302.1727" y="699.11584" z="598.42596" h="95"/>
       <object x="292.9067" y="699.0915" z="598.28394" h="96"/>
       <object x="296.53128" y="702.9941" z="598.38513" h="97"/>
    </spawn>
    <!-- Bakarma berseker-->
    <spawn map="320080000" npcid="213557" pool="2" interval="1200">
       <object x="482.35425" y="627.47943" z="512.7152" h="92"/>
       <object x="292.47543" y="590.91815" z="510.46664" h="89"/>
    </spawn>
    <!-- Tiny drakie-->
    <spawn map="320080000" npcid="213563" pool="14" interval="1200">
       <object x="276.10678" y="526.61786" z="506.35715" h="96"/>
       <object x="272.0409" y="520.47" z="504.62793" h="68"/>
       <object x="265.05612" y="510.87167" z="504.71625" h="86"/>
       <object x="263.71637" y="506.02936" z="503.58813" h="83"/>
       <object x="241.3676" y="524.2585" z="505.63394" h="66"/>
       <object x="246.92798" y="536.7066" z="507.47964" h="30"/>
       <object x="233.66818" y="537.8236" z="508.94833" h="54"/>
       <object x="230.41321" y="519.6532" z="507.4847" h="77"/>
       <object x="259.60977" y="549.0936" z="510.74643" h="56"/>
       <object x="278.65414" y="535.57074" z="509.30853" h="0"/>
       <object x="214.43475" y="454.67328" z="511.67914" h="97"/>
       <object x="225.21626" y="461.99194" z="508.46848" h="70"/>
       <object x="263.81274" y="444.18094" z="514.14923" h="110"/>
       <object x="254.28918" y="454.80176" z="509.33633" h="68"/>
    </spawn>
    <!--Unstable drakie -->
    <spawn map="320080000" npcid="213564" pool="38" interval="1200">
       <object x="278.94156" y="529.15485" z="507.3288" h="109"/>
       <object x="283.87134" y="530.2957" z="508.18503" h="8"/>
       <object x="285.63354" y="534.44714" z="509.3193" h="30"/>
       <object x="283.78214" y="538.0165" z="509.87772" h="50"/>
       <object x="280.06885" y="538.1512" z="509.50983" h="65"/>
       <object x="274.10928" y="535.01324" z="507.84833" h="74"/>
       <object x="270.16766" y="534.0197" z="507.4812" h="61"/>
       <object x="270.10486" y="529.4516" z="506.3305" h="93"/>
       <object x="267.28802" y="520.7739" z="504.2494" h="83"/>
       <object x="269.6694" y="516.18695" z="504.47372" h="102"/>
       <object x="268.86505" y="509.8085" z="504.42303" h="84"/>
       <object x="270.45688" y="507.3035" z="504.4519" h="102"/>
       <object x="259.39227" y="508.73642" z="503.63855" h="49"/>
       <object x="259.13065" y="501.25125" z="502.7544" h="96"/>
       <object x="263.0535" y="497.3765" z="503.20447" h="106"/>
       <object x="233.06226" y="523.84216" z="507.28876" h="71"/>
       <object x="231.00594" y="527.5224" z="507.75522" h="36"/>
       <object x="230.77077" y="534.52545" z="508.352" h="33"/>
       <object x="232.93759" y="540.77985" z="509.12128" h="4"/>
       <object x="241.48431" y="542.1022" z="508.9728" h="116"/>
       <object x="240.51718" y="533.897" z="507.13052" h="74"/>
       <object x="239.45412" y="529.6764" z="506.3408" h="85"/>
       <object x="248.73735" y="540.1687" z="507.96698" h="32"/>
       <object x="249.99411" y="545.63385" z="509.01575" h="23"/>
       <object x="254.38132" y="549.35284" z="510.03824" h="17"/>
       <object x="257.268" y="538.6602" z="506.56418" h="79"/>
       <object x="251.4164" y="528.861" z="504.91302" h="86"/>
       <object x="241.38252" y="515.46545" z="504.20764" h="59"/>
       <object x="259.64072" y="456.0789" z="509.18112" h="111"/>
       <object x="260.86896" y="448.9719" z="511.85864" h="80"/>
       <object x="251.59879" y="441.8999" z="512.8118" h="81"/>
       <object x="259.12955" y="439.48996" z="514.04254" h="2"/>
       <object x="248.33269" y="452.47897" z="509.17383" h="52"/>
       <object x="224.90318" y="457.86194" z="509.12872" h="57"/>
       <object x="215.75195" y="461.87378" z="510.73575" h="60"/>
       <object x="214.40569" y="468.0917" z="510.81143" h="31"/>
       <object x="223.25038" y="467.01187" z="508.5152" h="113"/>
       <object x="211.71712" y="451.9751" z="511.92554" h="81"/>
    </spawn>
    <!-- boss -->
    <!-- Lazy Dragashum-->
    <spawn map="320080000" npcid="213774" pool="1" interval="2400">
       <object x="547.7762" y="418.7222" z="616.7117" h="32"/>
    </spawn>
    <!--Protector Rakkan -->
    <spawn map="320080000" npcid="213771" pool="1" interval="2400">
       <object x="497.0058" y="434.71323" z="616.5837" h="71"/>
    </spawn>
    <!--Dragonpriest Tairgus -->
    <spawn map="320080000" npcid="213773" pool="1" interval="2400">
       <object x="380.69363" y="611.95557" z="598.5229" h="98"/>
    </spawn>
    <!-- Instructor Afrane-->
    <spawn map="320080000" npcid="213776" pool="1" interval="2400">
       <object x="255.62642" y="698.7573" z="600.9462" h="113"/>
    </spawn>
    <!-- Hungry Ooze-->
    <spawn map="320080000" npcid="213587" pool="1" interval="2400">
       <object x="567.4385" y="700.87506" z="538.70123" h="7"/>
    </spawn>
    <!-- Shadowmaster Takrin-->
    <spawn map="320080000" npcid="213772" pool="1" interval="2400">
       <object x="557.164" y="620.3145" z="578.3563" h="78"/>
    </spawn>
   <!-- Greatscholar Jaadis-->
    <spawn map="320080000" npcid="213775" pool="1" interval="2400">
       <object x="485.35547" y="595.45905" z="514.253" h="5"/>
    </spawn>
    <!--Kind Saraswati -->
    <spawn map="320080000" npcid="213802" pool="1" interval="2400">
       <object x="236.36742" y="448.51392" z="509.3445" h="24"/>
    </spawn>
    <!--Beautiful Lakshmi -->
    <spawn map="320080000" npcid="213778" pool="1" interval="2400">
       <object x="131.04027" y="586.6768" z="501.58148" h="3"/>
    </spawn>
    <!-- Lucky Golden Saam-->
    <spawn map="320080000" npcid="213588" pool="1" interval="2400">
       <object x="166.80019" y="536.28455" z="505.8016" h="9"/>
    </spawn>
    <!-- Commander Nimbarka-->
    <spawn map="320080000" npcid="213779" pool="1" interval="2400">
       <object x="186.18234" y="720.8597" z="529.7642" h="99"/>
    </spawn>
    <!-- Deputy Brigade General Yavant-->
    <spawn map="320080000" npcid="214026" pool="1" interval="2400">
       <object x="767.75543" y="427.97748" z="321.62454" h="55"/>
    </spawn>
    <!--Commander Bakarma -->
    <spawn map="320080000" npcid="213780" pool="1" interval="2400">
       <object x="813.18884" y="432.25464" z="318.9277" h="30"/>
    </spawn>
    <!--NPC-->
    <!--Ripley -->
    <spawn map="320080000" npcid="204828" pool="1" interval="2400">
       <object x="201.78842" y="374.16553" z="511.00385" h="30"/>
    </spawn>
    <!--Fafner -->
    <spawn map="320080000" npcid="204807" pool="1" interval="2400">
       <object x="488.87683" y="379.0808" z="621.8663" h="30"/>
    </spawn>
    <!--Balaur Bio Weapon -->
    <spawn map="320080000" npcid="700354" pool="1" interval="2400">
       <object x="499.5211" y="604.9554" z="513.0231" h="30"/>
    </spawn>
    <!--Bloodfury Booster -->
    <spawn map="320080000" npcid="700296" pool="1" interval="2400">
       <object x="315.32364" y="682.1332" z="596.8372" h="30"/>
    </spawn>
</spawns>
